{"Mustela putorius": {"Head": {"Color": "brown", "Shape": "triangular", "Quantity": "1", "Special Attribute": "There are two small round ears on top of the head"}, "Body": {"Color": "dark brown", "Shape": "elongated", "Quantity": "1", "Special Attribute": "Covered in thick fur"}, "Foot": {"Color": "black", "Shape": "paw-like", "Quantity": "4", "Special Attribute": "Sharp claws for climbing and digging"}, "Tail": {"Color": "black", "Shape": "long and bushy", "Quantity": "1", "Special Attribute": "Used for balance and communication"}}, "Relationship": ["Head is/up/to Body", "Foot is/next/to Body", "Foot is/next/to Body", "Foot is/next/to Body", "Foot is/next/to Body", "Tail is/behind/of Body"]}